similator-0.2.0.dist-info/METADATA
similator-0.2.0.dist-info/WHEEL
similator-0.2.0.dist-info/licenses/LICENSE
similator/__init__.py
similator/memory.py
similator/text_similator.py
similator/valid_data.py
similator/_rst_similator.pypy38-pp73-s390x-linux-gnu.so
similator-0.2.0.dist-info/RECORD
