Metadata-Version: 2.3
Name: similator
Version: 0.2.0
Classifier: Programming Language :: Rust
Classifier: Programming Language :: Python :: Implementation :: CPython
Classifier: Programming Language :: Python :: Implementation :: PyPy
Requires-Dist: pytest ; extra == 'dev'
Requires-Dist: maturin ; extra == 'dev'
Requires-Dist: furo ; extra == 'dev'
Requires-Dist: sphinx ; extra == 'dev'
Requires-Dist: twine >=5.1.1 ; extra == 'dev'
Requires-Dist: myst-parser ; extra == 'dev'
Requires-Dist: sphinx-autodoc-typehints ; extra == 'dev'
Provides-Extra: dev
License-File: LICENSE
Summary: A powerful text similarity module with Rust optimizations.
Keywords: similarity,similar,fuzzy,validate,search,compare,text
Author-email: Diego San Andres Vasco <sanandresvascodiego@gmail.com>
Requires-Python: >=3.8
